Flask_Bootstraps-3.3.7.8.dist-info/DESCRIPTION.rst
Flask_Bootstraps-3.3.7.8.dist-info/METADATA
Flask_Bootstraps-3.3.7.8.dist-info/RECORD
Flask_Bootstraps-3.3.7.8.dist-info/WHEEL
Flask_Bootstraps-3.3.7.8.dist-info/metadata.json
Flask_Bootstraps-3.3.7.8.dist-info/top_level.txt
flask_bootstraps/__init__.py
flask_bootstraps/forms.py
flask_bootstraps/nav.py
flask_bootstraps/static/css/bootstrap-theme.css
flask_bootstraps/static/css/bootstrap-theme.css.map
flask_bootstraps/static/css/bootstrap-theme.min.css
flask_bootstraps/static/css/bootstrap.css
flask_bootstraps/static/css/bootstrap.css.map
flask_bootstraps/static/css/bootstrap.min.css
flask_bootstraps/static/css/bootstrap.min.css.map
flask_bootstraps/static/css.bak/bootstrap-theme.css
flask_bootstraps/static/css.bak/bootstrap-theme.css.map
flask_bootstraps/static/css.bak/bootstrap-theme.min.css
flask_bootstraps/static/css.bak/bootstrap.css
flask_bootstraps/static/css.bak/bootstrap.css.map
flask_bootstraps/static/css.bak/bootstrap.min.css
flask_bootstraps/static/fonts/glyphicons-halflings-regular.eot
flask_bootstraps/static/fonts/glyphicons-halflings-regular.svg
flask_bootstraps/static/fonts/glyphicons-halflings-regular.ttf
flask_bootstraps/static/fonts/glyphicons-halflings-regular.woff
flask_bootstraps/static/fonts/glyphicons-halflings-regular.woff2
flask_bootstraps/static/js/bootstrap.js
flask_bootstraps/static/js/bootstrap.min.js
flask_bootstraps/static/js/html5shiv.min.js
flask_bootstraps/static/js/init.js
flask_bootstraps/static/js/init_if_le_ie.js
flask_bootstraps/static/js/jquery.js
flask_bootstraps/static/js/jquery.min.js
flask_bootstraps/static/js/jquery.min.map
flask_bootstraps/static/js/moment.js
flask_bootstraps/static/js/npm.js
flask_bootstraps/static/js/require.js
flask_bootstraps/static/js/respond.min.js
flask_bootstraps/templates/bootstrap/base.html
flask_bootstraps/templates/bootstrap/fixes.html
flask_bootstraps/templates/bootstrap/google.html
flask_bootstraps/templates/bootstrap/pagination.html
flask_bootstraps/templates/bootstrap/utils.html
flask_bootstraps/templates/bootstrap/wtf.html
