Metadata-Version: 2.0
Name: Flask-Bootstraps
Version: 3.3.7.8
Summary: An extension that includes Bootstrap in your project, without any boilerplate code.
Home-page: https://github.com/CptJason/flask-bootstraps
Author: CptJason
Author-email: beez.jason@gmail.com
License: BSD
Platform: any
Classifier: Environment :: Web Environment
Classifier: Intended Audience :: Developers
Classifier: License :: OSI Approved :: BSD License
Classifier: Operating System :: OS Independent
Classifier: Programming Language :: Python
Classifier: Programming Language :: Python :: 2
Classifier: Programming Language :: Python :: 3
Classifier: Topic :: Internet :: WWW/HTTP :: Dynamic Content
Classifier: Topic :: Software Development :: Libraries :: Python Modules
Requires-Dist: Flask (>=0.8)
Requires-Dist: dominate
Requires-Dist: visitor
